{
  "image_path": "data/synthetic_v2_large/sample_000854_jpn.png",
  "annotations": [
    {
      "markup_type": "circle",
      "subtype": "standard",
      "bbox": [
        35,
        109,
        134,
        134
      ],
      "text": "コンピュータビジョンは人工知能の分野です。",
      "color": null
    },
    {
      "markup_type": "highlight",
      "subtype": "pink",
      "bbox": [
        50,
        53,
        140,
        7
      ],
      "text": "ディープニューラルネットワークは画像処理を革新しました。",
      "color": [
        255,
        182,
        193
      ]
    }
  ],
  "metadata": {
    "language": "jpn",
    "num_lines": 5,
    "num_markups": 2,
    "index": 854
  }
}