{
  "image_path": "data/synthetic_v2_large/sample_001023_chi_sim.png",
  "annotations": [
    {
      "markup_type": "strikethrough",
      "subtype": "double",
      "bbox": [
        50,
        52,
        80,
        8
      ],
      "text": "计算机视觉是人工智能的一个领域。",
      "color": null
    },
    {
      "markup_type": "highlight",
      "subtype": "green",
      "bbox": [
        50,
        53,
        80,
        7
      ],
      "text": "计算机视觉是人工智能的一个领域。",
      "color": [
        144,
        238,
        144
      ]
    }
  ],
  "metadata": {
    "language": "chi_sim",
    "num_lines": 4,
    "num_markups": 2,
    "index": 1023
  }
}