{
  "image_path": "data/synthetic_v2_large/sample_000334_jpn.png",
  "annotations": [
    {
      "markup_type": "rectangle",
      "subtype": "standard",
      "bbox": [
        35,
        158,
        170,
        37
      ],
      "text": "ディープニューラルネットワークは画像処理を革新しました。",
      "color": null
    },
    {
      "markup_type": "circle",
      "subtype": "standard",
      "bbox": [
        35,
        91,
        170,
        170
      ],
      "text": "ディープニューラルネットワークは画像処理を革新しました。",
      "color": null
    },
    {
      "markup_type": "underline",
      "subtype": "single",
      "bbox": [
        50,
        186,
        140,
        4
      ],
      "text": "ディープニューラルネットワークは画像処理を革新しました。",
      "color": null
    }
  ],
  "metadata": {
    "language": "jpn",
    "num_lines": 8,
    "num_markups": 3,
    "index": 334
  }
}