{
  "image_path": "data/synthetic_v2_large/sample_003290_eng.png",
  "annotations": [
    {
      "markup_type": "circle",
      "subtype": "standard",
      "bbox": [
        35,
        92,
        290,
        290
      ],
      "text": "Machine learning algorithms can detect patterns in data.",
      "color": null
    },
    {
      "markup_type": "highlight",
      "subtype": "pink",
      "bbox": [
        50,
        232,
        261,
        10
      ],
      "text": "Machine learning algorithms can detect patterns in data.",
      "color": [
        255,
        182,
        193
      ]
    }
  ],
  "metadata": {
    "language": "eng",
    "num_lines": 7,
    "num_markups": 2,
    "index": 3290
  }
}