{
  "image_path": "data/synthetic_v2_large/sample_006294_eng.png",
  "annotations": [
    {
      "markup_type": "rectangle",
      "subtype": "standard",
      "bbox": [
        35,
        96,
        256,
        41
      ],
      "text": "Computer vision is a field of artificial intelligence.",
      "color": null
    },
    {
      "markup_type": "strikethrough",
      "subtype": "single",
      "bbox": [
        50,
        293,
        285,
        8
      ],
      "text": "Deep neural networks have revolutionized image processing.",
      "color": null
    },
    {
      "markup_type": "highlight",
      "subtype": "green",
      "bbox": [
        50,
        51,
        300,
        11
      ],
      "text": "Optical character recognition enables text extraction from images.",
      "color": [
        144,
        238,
        144
      ]
    }
  ],
  "metadata": {
    "language": "eng",
    "num_lines": 5,
    "num_markups": 3,
    "index": 6294
  }
}